<?xml version="1.0" encoding="UTF-8"?>
<root>
  <item name="android.app.slice.Slice android.app.slice.SliceSpec getSpec()">
    <annotation name="android.support.annotation.Nullable" />
  </item>
  <item name="android.app.slice.Slice java.util.List&lt;java.lang.String&gt; getHints()">
    <annotation name="android.support.annotation.StringDef">
      <val name="value" val="{android.app.slice.Slice.HINT_TITLE, android.app.slice.Slice.HINT_LIST, android.app.slice.Slice.HINT_LIST_ITEM, android.app.slice.Slice.HINT_LARGE, android.app.slice.Slice.HINT_ACTIONS, android.app.slice.Slice.HINT_SELECTED, android.app.slice.Slice.HINT_NO_TINT, android.app.slice.Slice.HINT_SHORTCUT, android.app.slice.Slice.HINT_HORIZONTAL, android.app.slice.Slice.HINT_PARTIAL, android.app.slice.Slice.HINT_SEE_MORE, android.app.slice.Slice.HINT_KEYWORDS, android.app.slice.Slice.HINT_ERROR, android.app.slice.Slice.HINT_TTL, android.app.slice.Slice.HINT_LAST_UPDATED, android.app.slice.Slice.HINT_PERMISSION_REQUEST}" />
    </annotation>
  </item>
  <item name="android.app.slice.Slice.Builder Builder(android.app.slice.Slice.Builder) 0">
    <annotation name="android.support.annotation.NonNull" />
  </item>
  <item name="android.app.slice.Slice.Builder Builder(android.net.Uri, android.app.slice.SliceSpec) 0">
    <annotation name="android.support.annotation.NonNull" />
  </item>
  <item name="android.app.slice.Slice.Builder android.app.slice.Slice.Builder addAction(android.app.PendingIntent, android.app.slice.Slice, java.lang.String) 0">
    <annotation name="android.support.annotation.NonNull" />
  </item>
  <item name="android.app.slice.Slice.Builder android.app.slice.Slice.Builder addAction(android.app.PendingIntent, android.app.slice.Slice, java.lang.String) 1">
    <annotation name="android.support.annotation.NonNull" />
  </item>
  <item name="android.app.slice.Slice.Builder android.app.slice.Slice.Builder addAction(android.app.PendingIntent, android.app.slice.Slice, java.lang.String) 2">
    <annotation name="android.support.annotation.Nullable" />
    <annotation name="android.support.annotation.StringDef">
      <val name="value" val="{android.app.slice.Slice.SUBTYPE_COLOR, android.app.slice.Slice.SUBTYPE_CONTENT_DESCRIPTION, android.app.slice.Slice.SUBTYPE_MAX, android.app.slice.Slice.SUBTYPE_MESSAGE, android.app.slice.Slice.SUBTYPE_PRIORITY, android.app.slice.Slice.SUBTYPE_RANGE, android.app.slice.Slice.SUBTYPE_SOURCE, android.app.slice.Slice.SUBTYPE_TOGGLE, android.app.slice.Slice.SUBTYPE_VALUE, android.app.slice.Slice.SUBTYPE_LAYOUT_DIRECTION}" />
    </annotation>
  </item>
  <item name="android.app.slice.Slice.Builder android.app.slice.Slice.Builder addBundle(android.os.Bundle, java.lang.String, java.util.List&lt;java.lang.String&gt;) 1">
    <annotation name="android.support.annotation.Nullable" />
    <annotation name="android.support.annotation.StringDef">
      <val name="value" val="{android.app.slice.Slice.SUBTYPE_COLOR, android.app.slice.Slice.SUBTYPE_CONTENT_DESCRIPTION, android.app.slice.Slice.SUBTYPE_MAX, android.app.slice.Slice.SUBTYPE_MESSAGE, android.app.slice.Slice.SUBTYPE_PRIORITY, android.app.slice.Slice.SUBTYPE_RANGE, android.app.slice.Slice.SUBTYPE_SOURCE, android.app.slice.Slice.SUBTYPE_TOGGLE, android.app.slice.Slice.SUBTYPE_VALUE, android.app.slice.Slice.SUBTYPE_LAYOUT_DIRECTION}" />
    </annotation>
  </item>
  <item name="android.app.slice.Slice.Builder android.app.slice.Slice.Builder addBundle(android.os.Bundle, java.lang.String, java.util.List&lt;java.lang.String&gt;) 2">
    <annotation name="android.support.annotation.StringDef">
      <val name="value" val="{android.app.slice.Slice.HINT_TITLE, android.app.slice.Slice.HINT_LIST, android.app.slice.Slice.HINT_LIST_ITEM, android.app.slice.Slice.HINT_LARGE, android.app.slice.Slice.HINT_ACTIONS, android.app.slice.Slice.HINT_SELECTED, android.app.slice.Slice.HINT_NO_TINT, android.app.slice.Slice.HINT_SHORTCUT, android.app.slice.Slice.HINT_HORIZONTAL, android.app.slice.Slice.HINT_PARTIAL, android.app.slice.Slice.HINT_SEE_MORE, android.app.slice.Slice.HINT_KEYWORDS, android.app.slice.Slice.HINT_ERROR, android.app.slice.Slice.HINT_TTL, android.app.slice.Slice.HINT_LAST_UPDATED, android.app.slice.Slice.HINT_PERMISSION_REQUEST}" />
    </annotation>
  </item>
  <item name="android.app.slice.Slice.Builder android.app.slice.Slice.Builder addHints(java.util.List&lt;java.lang.String&gt;) 0">
    <annotation name="android.support.annotation.StringDef">
      <val name="value" val="{android.app.slice.Slice.HINT_TITLE, android.app.slice.Slice.HINT_LIST, android.app.slice.Slice.HINT_LIST_ITEM, android.app.slice.Slice.HINT_LARGE, android.app.slice.Slice.HINT_ACTIONS, android.app.slice.Slice.HINT_SELECTED, android.app.slice.Slice.HINT_NO_TINT, android.app.slice.Slice.HINT_SHORTCUT, android.app.slice.Slice.HINT_HORIZONTAL, android.app.slice.Slice.HINT_PARTIAL, android.app.slice.Slice.HINT_SEE_MORE, android.app.slice.Slice.HINT_KEYWORDS, android.app.slice.Slice.HINT_ERROR, android.app.slice.Slice.HINT_TTL, android.app.slice.Slice.HINT_LAST_UPDATED, android.app.slice.Slice.HINT_PERMISSION_REQUEST}" />
    </annotation>
  </item>
  <item name="android.app.slice.Slice.Builder android.app.slice.Slice.Builder addIcon(android.graphics.drawable.Icon, java.lang.String, java.util.List&lt;java.lang.String&gt;) 1">
    <annotation name="android.support.annotation.Nullable" />
    <annotation name="android.support.annotation.StringDef">
      <val name="value" val="{android.app.slice.Slice.SUBTYPE_COLOR, android.app.slice.Slice.SUBTYPE_CONTENT_DESCRIPTION, android.app.slice.Slice.SUBTYPE_MAX, android.app.slice.Slice.SUBTYPE_MESSAGE, android.app.slice.Slice.SUBTYPE_PRIORITY, android.app.slice.Slice.SUBTYPE_RANGE, android.app.slice.Slice.SUBTYPE_SOURCE, android.app.slice.Slice.SUBTYPE_TOGGLE, android.app.slice.Slice.SUBTYPE_VALUE, android.app.slice.Slice.SUBTYPE_LAYOUT_DIRECTION}" />
    </annotation>
  </item>
  <item name="android.app.slice.Slice.Builder android.app.slice.Slice.Builder addIcon(android.graphics.drawable.Icon, java.lang.String, java.util.List&lt;java.lang.String&gt;) 2">
    <annotation name="android.support.annotation.StringDef">
      <val name="value" val="{android.app.slice.Slice.HINT_TITLE, android.app.slice.Slice.HINT_LIST, android.app.slice.Slice.HINT_LIST_ITEM, android.app.slice.Slice.HINT_LARGE, android.app.slice.Slice.HINT_ACTIONS, android.app.slice.Slice.HINT_SELECTED, android.app.slice.Slice.HINT_NO_TINT, android.app.slice.Slice.HINT_SHORTCUT, android.app.slice.Slice.HINT_HORIZONTAL, android.app.slice.Slice.HINT_PARTIAL, android.app.slice.Slice.HINT_SEE_MORE, android.app.slice.Slice.HINT_KEYWORDS, android.app.slice.Slice.HINT_ERROR, android.app.slice.Slice.HINT_TTL, android.app.slice.Slice.HINT_LAST_UPDATED, android.app.slice.Slice.HINT_PERMISSION_REQUEST}" />
    </annotation>
  </item>
  <item name="android.app.slice.Slice.Builder android.app.slice.Slice.Builder addInt(int, java.lang.String, java.util.List&lt;java.lang.String&gt;) 1">
    <annotation name="android.support.annotation.Nullable" />
    <annotation name="android.support.annotation.StringDef">
      <val name="value" val="{android.app.slice.Slice.SUBTYPE_COLOR, android.app.slice.Slice.SUBTYPE_CONTENT_DESCRIPTION, android.app.slice.Slice.SUBTYPE_MAX, android.app.slice.Slice.SUBTYPE_MESSAGE, android.app.slice.Slice.SUBTYPE_PRIORITY, android.app.slice.Slice.SUBTYPE_RANGE, android.app.slice.Slice.SUBTYPE_SOURCE, android.app.slice.Slice.SUBTYPE_TOGGLE, android.app.slice.Slice.SUBTYPE_VALUE, android.app.slice.Slice.SUBTYPE_LAYOUT_DIRECTION}" />
    </annotation>
  </item>
  <item name="android.app.slice.Slice.Builder android.app.slice.Slice.Builder addInt(int, java.lang.String, java.util.List&lt;java.lang.String&gt;) 2">
    <annotation name="android.support.annotation.StringDef">
      <val name="value" val="{android.app.slice.Slice.HINT_TITLE, android.app.slice.Slice.HINT_LIST, android.app.slice.Slice.HINT_LIST_ITEM, android.app.slice.Slice.HINT_LARGE, android.app.slice.Slice.HINT_ACTIONS, android.app.slice.Slice.HINT_SELECTED, android.app.slice.Slice.HINT_NO_TINT, android.app.slice.Slice.HINT_SHORTCUT, android.app.slice.Slice.HINT_HORIZONTAL, android.app.slice.Slice.HINT_PARTIAL, android.app.slice.Slice.HINT_SEE_MORE, android.app.slice.Slice.HINT_KEYWORDS, android.app.slice.Slice.HINT_ERROR, android.app.slice.Slice.HINT_TTL, android.app.slice.Slice.HINT_LAST_UPDATED, android.app.slice.Slice.HINT_PERMISSION_REQUEST}" />
    </annotation>
  </item>
  <item name="android.app.slice.Slice.Builder android.app.slice.Slice.Builder addLong(long, java.lang.String, java.util.List&lt;java.lang.String&gt;) 1">
    <annotation name="android.support.annotation.Nullable" />
    <annotation name="android.support.annotation.StringDef">
      <val name="value" val="{android.app.slice.Slice.SUBTYPE_COLOR, android.app.slice.Slice.SUBTYPE_CONTENT_DESCRIPTION, android.app.slice.Slice.SUBTYPE_MAX, android.app.slice.Slice.SUBTYPE_MESSAGE, android.app.slice.Slice.SUBTYPE_PRIORITY, android.app.slice.Slice.SUBTYPE_RANGE, android.app.slice.Slice.SUBTYPE_SOURCE, android.app.slice.Slice.SUBTYPE_TOGGLE, android.app.slice.Slice.SUBTYPE_VALUE, android.app.slice.Slice.SUBTYPE_LAYOUT_DIRECTION}" />
    </annotation>
  </item>
  <item name="android.app.slice.Slice.Builder android.app.slice.Slice.Builder addLong(long, java.lang.String, java.util.List&lt;java.lang.String&gt;) 2">
    <annotation name="android.support.annotation.StringDef">
      <val name="value" val="{android.app.slice.Slice.HINT_TITLE, android.app.slice.Slice.HINT_LIST, android.app.slice.Slice.HINT_LIST_ITEM, android.app.slice.Slice.HINT_LARGE, android.app.slice.Slice.HINT_ACTIONS, android.app.slice.Slice.HINT_SELECTED, android.app.slice.Slice.HINT_NO_TINT, android.app.slice.Slice.HINT_SHORTCUT, android.app.slice.Slice.HINT_HORIZONTAL, android.app.slice.Slice.HINT_PARTIAL, android.app.slice.Slice.HINT_SEE_MORE, android.app.slice.Slice.HINT_KEYWORDS, android.app.slice.Slice.HINT_ERROR, android.app.slice.Slice.HINT_TTL, android.app.slice.Slice.HINT_LAST_UPDATED, android.app.slice.Slice.HINT_PERMISSION_REQUEST}" />
    </annotation>
  </item>
  <item name="android.app.slice.Slice.Builder android.app.slice.Slice.Builder addRemoteInput(android.app.RemoteInput, java.lang.String, java.util.List&lt;java.lang.String&gt;) 1">
    <annotation name="android.support.annotation.Nullable" />
    <annotation name="android.support.annotation.StringDef">
      <val name="value" val="{android.app.slice.Slice.SUBTYPE_COLOR, android.app.slice.Slice.SUBTYPE_CONTENT_DESCRIPTION, android.app.slice.Slice.SUBTYPE_MAX, android.app.slice.Slice.SUBTYPE_MESSAGE, android.app.slice.Slice.SUBTYPE_PRIORITY, android.app.slice.Slice.SUBTYPE_RANGE, android.app.slice.Slice.SUBTYPE_SOURCE, android.app.slice.Slice.SUBTYPE_TOGGLE, android.app.slice.Slice.SUBTYPE_VALUE, android.app.slice.Slice.SUBTYPE_LAYOUT_DIRECTION}" />
    </annotation>
  </item>
  <item name="android.app.slice.Slice.Builder android.app.slice.Slice.Builder addRemoteInput(android.app.RemoteInput, java.lang.String, java.util.List&lt;java.lang.String&gt;) 2">
    <annotation name="android.support.annotation.StringDef">
      <val name="value" val="{android.app.slice.Slice.HINT_TITLE, android.app.slice.Slice.HINT_LIST, android.app.slice.Slice.HINT_LIST_ITEM, android.app.slice.Slice.HINT_LARGE, android.app.slice.Slice.HINT_ACTIONS, android.app.slice.Slice.HINT_SELECTED, android.app.slice.Slice.HINT_NO_TINT, android.app.slice.Slice.HINT_SHORTCUT, android.app.slice.Slice.HINT_HORIZONTAL, android.app.slice.Slice.HINT_PARTIAL, android.app.slice.Slice.HINT_SEE_MORE, android.app.slice.Slice.HINT_KEYWORDS, android.app.slice.Slice.HINT_ERROR, android.app.slice.Slice.HINT_TTL, android.app.slice.Slice.HINT_LAST_UPDATED, android.app.slice.Slice.HINT_PERMISSION_REQUEST}" />
    </annotation>
  </item>
  <item name="android.app.slice.Slice.Builder android.app.slice.Slice.Builder addSubSlice(android.app.slice.Slice, java.lang.String) 0">
    <annotation name="android.support.annotation.NonNull" />
  </item>
  <item name="android.app.slice.Slice.Builder android.app.slice.Slice.Builder addSubSlice(android.app.slice.Slice, java.lang.String) 1">
    <annotation name="android.support.annotation.Nullable" />
    <annotation name="android.support.annotation.StringDef">
      <val name="value" val="{android.app.slice.Slice.SUBTYPE_COLOR, android.app.slice.Slice.SUBTYPE_CONTENT_DESCRIPTION, android.app.slice.Slice.SUBTYPE_MAX, android.app.slice.Slice.SUBTYPE_MESSAGE, android.app.slice.Slice.SUBTYPE_PRIORITY, android.app.slice.Slice.SUBTYPE_RANGE, android.app.slice.Slice.SUBTYPE_SOURCE, android.app.slice.Slice.SUBTYPE_TOGGLE, android.app.slice.Slice.SUBTYPE_VALUE, android.app.slice.Slice.SUBTYPE_LAYOUT_DIRECTION}" />
    </annotation>
  </item>
  <item name="android.app.slice.Slice.Builder android.app.slice.Slice.Builder addText(java.lang.CharSequence, java.lang.String, java.util.List&lt;java.lang.String&gt;) 1">
    <annotation name="android.support.annotation.Nullable" />
    <annotation name="android.support.annotation.StringDef">
      <val name="value" val="{android.app.slice.Slice.SUBTYPE_COLOR, android.app.slice.Slice.SUBTYPE_CONTENT_DESCRIPTION, android.app.slice.Slice.SUBTYPE_MAX, android.app.slice.Slice.SUBTYPE_MESSAGE, android.app.slice.Slice.SUBTYPE_PRIORITY, android.app.slice.Slice.SUBTYPE_RANGE, android.app.slice.Slice.SUBTYPE_SOURCE, android.app.slice.Slice.SUBTYPE_TOGGLE, android.app.slice.Slice.SUBTYPE_VALUE, android.app.slice.Slice.SUBTYPE_LAYOUT_DIRECTION}" />
    </annotation>
  </item>
  <item name="android.app.slice.Slice.Builder android.app.slice.Slice.Builder addText(java.lang.CharSequence, java.lang.String, java.util.List&lt;java.lang.String&gt;) 2">
    <annotation name="android.support.annotation.StringDef">
      <val name="value" val="{android.app.slice.Slice.HINT_TITLE, android.app.slice.Slice.HINT_LIST, android.app.slice.Slice.HINT_LIST_ITEM, android.app.slice.Slice.HINT_LARGE, android.app.slice.Slice.HINT_ACTIONS, android.app.slice.Slice.HINT_SELECTED, android.app.slice.Slice.HINT_NO_TINT, android.app.slice.Slice.HINT_SHORTCUT, android.app.slice.Slice.HINT_HORIZONTAL, android.app.slice.Slice.HINT_PARTIAL, android.app.slice.Slice.HINT_SEE_MORE, android.app.slice.Slice.HINT_KEYWORDS, android.app.slice.Slice.HINT_ERROR, android.app.slice.Slice.HINT_TTL, android.app.slice.Slice.HINT_LAST_UPDATED, android.app.slice.Slice.HINT_PERMISSION_REQUEST}" />
    </annotation>
  </item>
  <item name="android.app.slice.SliceItem boolean hasHint(java.lang.String) 0">
    <annotation name="android.support.annotation.StringDef">
      <val name="value" val="{android.app.slice.Slice.HINT_TITLE, android.app.slice.Slice.HINT_LIST, android.app.slice.Slice.HINT_LIST_ITEM, android.app.slice.Slice.HINT_LARGE, android.app.slice.Slice.HINT_ACTIONS, android.app.slice.Slice.HINT_SELECTED, android.app.slice.Slice.HINT_NO_TINT, android.app.slice.Slice.HINT_SHORTCUT, android.app.slice.Slice.HINT_HORIZONTAL, android.app.slice.Slice.HINT_PARTIAL, android.app.slice.Slice.HINT_SEE_MORE, android.app.slice.Slice.HINT_KEYWORDS, android.app.slice.Slice.HINT_ERROR, android.app.slice.Slice.HINT_TTL, android.app.slice.Slice.HINT_LAST_UPDATED, android.app.slice.Slice.HINT_PERMISSION_REQUEST}" />
    </annotation>
  </item>
  <item name="android.app.slice.SliceItem java.util.List&lt;java.lang.String&gt; getHints()">
    <annotation name="android.support.annotation.NonNull" />
    <annotation name="android.support.annotation.StringDef">
      <val name="value" val="{android.app.slice.Slice.HINT_TITLE, android.app.slice.Slice.HINT_LIST, android.app.slice.Slice.HINT_LIST_ITEM, android.app.slice.Slice.HINT_LARGE, android.app.slice.Slice.HINT_ACTIONS, android.app.slice.Slice.HINT_SELECTED, android.app.slice.Slice.HINT_NO_TINT, android.app.slice.Slice.HINT_SHORTCUT, android.app.slice.Slice.HINT_HORIZONTAL, android.app.slice.Slice.HINT_PARTIAL, android.app.slice.Slice.HINT_SEE_MORE, android.app.slice.Slice.HINT_KEYWORDS, android.app.slice.Slice.HINT_ERROR, android.app.slice.Slice.HINT_TTL, android.app.slice.Slice.HINT_LAST_UPDATED, android.app.slice.Slice.HINT_PERMISSION_REQUEST}" />
    </annotation>
  </item>
  <item name="android.app.slice.SliceManager">
  </item>
  <item name="android.app.slice.SliceManager android.app.slice.Slice bindSlice(android.content.Intent, java.util.Set&lt;android.app.slice.SliceSpec&gt;)">
    <annotation name="android.support.annotation.Nullable" />
  </item>
  <item name="android.app.slice.SliceManager android.app.slice.Slice bindSlice(android.content.Intent, java.util.Set&lt;android.app.slice.SliceSpec&gt;) 0">
    <annotation name="android.support.annotation.NonNull" />
  </item>
  <item name="android.app.slice.SliceManager android.app.slice.Slice bindSlice(android.content.Intent, java.util.Set&lt;android.app.slice.SliceSpec&gt;) 1">
    <annotation name="android.support.annotation.NonNull" />
  </item>
  <item name="android.app.slice.SliceManager android.app.slice.Slice bindSlice(android.net.Uri, java.util.Set&lt;android.app.slice.SliceSpec&gt;)">
    <annotation name="android.support.annotation.Nullable" />
  </item>
  <item name="android.app.slice.SliceManager android.app.slice.Slice bindSlice(android.net.Uri, java.util.Set&lt;android.app.slice.SliceSpec&gt;) 0">
    <annotation name="android.support.annotation.NonNull" />
  </item>
  <item name="android.app.slice.SliceManager android.app.slice.Slice bindSlice(android.net.Uri, java.util.Set&lt;android.app.slice.SliceSpec&gt;) 1">
    <annotation name="android.support.annotation.NonNull" />
  </item>
  <item name="android.app.slice.SliceManager android.net.Uri mapIntentToUri(android.content.Intent)">
    <annotation name="android.support.annotation.Nullable" />
  </item>
  <item name="android.app.slice.SliceManager android.net.Uri mapIntentToUri(android.content.Intent) 0">
    <annotation name="android.support.annotation.NonNull" />
  </item>
  <item name="android.app.slice.SliceManager int checkSlicePermission(android.net.Uri, int, int)">
    <annotation name="android.support.annotation.IntDef">
      <val name="value" val="{android.content.pm.PackageManager.PERMISSION_GRANTED, android.content.pm.PackageManager.PERMISSION_DENIED}" />
    </annotation>
  </item>
  <item name="android.app.slice.SliceManager int checkSlicePermission(android.net.Uri, int, int) 0">
    <annotation name="android.support.annotation.NonNull" />
  </item>
  <item name="android.app.slice.SliceManager java.util.Collection&lt;android.net.Uri&gt; getSliceDescendants(android.net.Uri)">
    <annotation name="android.support.annotation.NonNull" />
  </item>
  <item name="android.app.slice.SliceManager java.util.Collection&lt;android.net.Uri&gt; getSliceDescendants(android.net.Uri) 0">
    <annotation name="android.support.annotation.NonNull" />
  </item>
  <item name="android.app.slice.SliceManager java.util.List&lt;android.net.Uri&gt; getPinnedSlices()">
    <annotation name="android.support.annotation.NonNull" />
  </item>
  <item name="android.app.slice.SliceManager java.util.Set&lt;android.app.slice.SliceSpec&gt; getPinnedSpecs(android.net.Uri)">
    <annotation name="android.support.annotation.NonNull" />
  </item>
  <item name="android.app.slice.SliceManager void grantSlicePermission(java.lang.String, android.net.Uri) 0">
    <annotation name="android.support.annotation.NonNull" />
  </item>
  <item name="android.app.slice.SliceManager void grantSlicePermission(java.lang.String, android.net.Uri) 1">
    <annotation name="android.support.annotation.NonNull" />
  </item>
  <item name="android.app.slice.SliceManager void pinSlice(android.net.Uri, java.util.Set&lt;android.app.slice.SliceSpec&gt;) 0">
    <annotation name="android.support.annotation.NonNull" />
  </item>
  <item name="android.app.slice.SliceManager void pinSlice(android.net.Uri, java.util.Set&lt;android.app.slice.SliceSpec&gt;) 1">
    <annotation name="android.support.annotation.NonNull" />
  </item>
  <item name="android.app.slice.SliceManager void revokeSlicePermission(java.lang.String, android.net.Uri) 0">
    <annotation name="android.support.annotation.NonNull" />
  </item>
  <item name="android.app.slice.SliceManager void revokeSlicePermission(java.lang.String, android.net.Uri) 1">
    <annotation name="android.support.annotation.NonNull" />
  </item>
  <item name="android.app.slice.SliceManager void unpinSlice(android.net.Uri) 0">
    <annotation name="android.support.annotation.NonNull" />
  </item>
  <item name="android.app.slice.SliceMetrics SliceMetrics(android.content.Context, android.net.Uri) 0">
    <annotation name="android.support.annotation.NonNull" />
  </item>
  <item name="android.app.slice.SliceMetrics SliceMetrics(android.content.Context, android.net.Uri) 1">
    <annotation name="android.support.annotation.NonNull" />
  </item>
  <item name="android.app.slice.SliceMetrics void logTouch(int, android.net.Uri) 1">
    <annotation name="android.support.annotation.NonNull" />
  </item>
  <item name="android.app.slice.SliceProvider SliceProvider(java.lang.String...) 0">
    <annotation name="android.support.annotation.NonNull" />
  </item>
  <item name="android.app.slice.SliceProvider android.app.PendingIntent onCreatePermissionRequest(android.net.Uri)">
    <annotation name="android.support.annotation.NonNull" />
  </item>
  <item name="android.app.slice.SliceProvider android.net.Uri onMapIntentToUri(android.content.Intent)">
    <annotation name="android.support.annotation.NonNull" />
  </item>
  <item name="android.app.slice.SliceProvider java.util.Collection&lt;android.net.Uri&gt; onGetSliceDescendants(android.net.Uri)">
    <annotation name="android.support.annotation.NonNull" />
  </item>
  <item name="android.app.slice.SliceProvider java.util.Collection&lt;android.net.Uri&gt; onGetSliceDescendants(android.net.Uri) 0">
    <annotation name="android.support.annotation.NonNull" />
  </item>
  <item name="android.app.slice.SliceSpec SliceSpec(java.lang.String, int) 0">
    <annotation name="android.support.annotation.NonNull" />
  </item>
  <item name="android.app.slice.SliceSpec boolean canRender(android.app.slice.SliceSpec) 0">
    <annotation name="android.support.annotation.NonNull" />
  </item>
</root>

