<?xml version="1.0" encoding="UTF-8"?>
<issues format="5" by="lint 4.1.0-dev">

    <issue
        id="DefaultLocale"
        message="Implicitly using the default locale is a common source of bugs: Use `String.format(Locale, ...)` instead">
        <location
            file="src/com/android/tools/idea/uibuilder/handlers/absolute/AbsoluteDragTarget.java"
            line="32"/>
    </issue>

    <issue
        id="DefaultLocale"
        message="Implicitly using the default locale is a common source of bugs: Use `String.format(Locale, ...)` instead">
        <location
            file="src/com/android/tools/idea/uibuilder/handlers/absolute/AbsoluteDragTarget.java"
            line="33"/>
    </issue>

    <issue
        id="DefaultLocale"
        message="Implicitly using the default locale is a common source of bugs: Use `String.format(Locale, ...)` instead">
        <location
            file="src/com/android/tools/idea/uibuilder/handlers/absolute/AbsoluteResizeTarget.java"
            line="32"/>
    </issue>

    <issue
        id="DefaultLocale"
        message="Implicitly using the default locale is a common source of bugs: Use `String.format(Locale, ...)` instead">
        <location
            file="src/com/android/tools/idea/uibuilder/handlers/absolute/AbsoluteResizeTarget.java"
            line="36"/>
    </issue>

    <issue
        id="DefaultLocale"
        message="Implicitly using the default locale is a common source of bugs: Use `String.format(Locale, ...)` instead">
        <location
            file="src/com/android/tools/idea/uibuilder/scout/Connection.java"
            line="141"/>
    </issue>

    <issue
        id="DefaultLocale"
        message="Implicitly using the default locale is a common source of bugs: Use `String.format(Locale, ...)` instead">
        <location
            file="src/com/android/tools/idea/uibuilder/scout/ConstrainedWidget.java"
            line="86"/>
    </issue>

    <issue
        id="DefaultLocale"
        message="Implicitly using the default locale is a common source of bugs: Use `String.format(Locale, ...)` instead">
        <location
            file="src/com/android/tools/idea/uibuilder/handlers/constraint/targets/ConstraintAnchorTarget.java"
            line="438"/>
    </issue>

    <issue
        id="DefaultLocale"
        message="Implicitly using the default locale is a common source of bugs: Use `String.format(Locale, ...)` instead">
        <location
            file="src/com/android/tools/idea/uibuilder/handlers/constraint/ConstraintComponentUtilities.java"
            line="635"/>
    </issue>

    <issue
        id="DefaultLocale"
        message="Implicitly using the default locale is a common source of bugs: Use `String.format(Locale, ...)` instead">
        <location
            file="src/com/android/tools/idea/uibuilder/handlers/constraint/ConstraintComponentUtilities.java"
            line="760"/>
    </issue>

    <issue
        id="DefaultLocale"
        message="Implicitly using the default locale is a common source of bugs: Use `String.format(Locale, ...)` instead">
        <location
            file="src/com/android/tools/idea/uibuilder/handlers/constraint/ConstraintComponentUtilities.java"
            line="765"/>
    </issue>

    <issue
        id="DefaultLocale"
        message="Implicitly using the default locale is a common source of bugs: Use `String.format(Locale, ...)` instead">
        <location
            file="src/com/android/tools/idea/uibuilder/handlers/constraint/ConstraintComponentUtilities.java"
            line="827"/>
    </issue>

    <issue
        id="DefaultLocale"
        message="Implicitly using the default locale is a common source of bugs: Use `String.format(Locale, ...)` instead">
        <location
            file="src/com/android/tools/idea/uibuilder/handlers/constraint/ConstraintComponentUtilities.java"
            line="838"/>
    </issue>

    <issue
        id="DefaultLocale"
        message="Implicitly using the default locale is a common source of bugs: Use `String.format(Locale, ...)` instead">
        <location
            file="src/com/android/tools/idea/uibuilder/handlers/constraint/ConstraintComponentUtilities.java"
            line="1480"/>
    </issue>

    <issue
        id="DefaultLocale"
        message="Implicitly using the default locale is a common source of bugs: Use `String.format(Locale, ...)` instead">
        <location
            file="src/com/android/tools/idea/uibuilder/handlers/constraint/targets/ConstraintDragDndTarget.java"
            line="123"/>
    </issue>

    <issue
        id="DefaultLocale"
        message="Implicitly using the default locale is a common source of bugs: Use `String.format(Locale, ...)` instead">
        <location
            file="src/com/android/tools/idea/uibuilder/handlers/constraint/targets/ConstraintDragDndTarget.java"
            line="128"/>
    </issue>

    <issue
        id="DefaultLocale"
        message="Implicitly using the default locale is a common source of bugs: Use `String.format(Locale, ...)` instead">
        <location
            file="src/com/android/tools/idea/uibuilder/handlers/constraint/targets/ConstraintDragTarget.java"
            line="181"/>
    </issue>

    <issue
        id="DefaultLocale"
        message="Implicitly using the default locale is a common source of bugs: Use `String.format(Locale, ...)` instead">
        <location
            file="src/com/android/tools/idea/uibuilder/handlers/constraint/targets/ConstraintDragTarget.java"
            line="220"/>
    </issue>

    <issue
        id="DefaultLocale"
        message="Implicitly using the default locale is a common source of bugs: Use `String.format(Locale, ...)` instead">
        <location
            file="src/com/android/tools/idea/uibuilder/handlers/constraint/targets/ConstraintDragTarget.java"
            line="273"/>
    </issue>

    <issue
        id="DefaultLocale"
        message="Implicitly using the default locale is a common source of bugs: Use `String.format(Locale, ...)` instead">
        <location
            file="src/com/android/tools/idea/uibuilder/handlers/constraint/draw/ConstraintLayoutNotchProvider.java"
            line="109"/>
    </issue>

    <issue
        id="DefaultLocale"
        message="Implicitly using the default locale is a common source of bugs: Use `String.format(Locale, ...)` instead">
        <location
            file="src/com/android/tools/idea/uibuilder/handlers/constraint/draw/ConstraintLayoutNotchProvider.java"
            line="110"/>
    </issue>

    <issue
        id="DefaultLocale"
        message="Implicitly using the default locale is a common source of bugs: Use `String.format(Locale, ...)` instead">
        <location
            file="src/com/android/tools/idea/uibuilder/handlers/constraint/draw/ConstraintLayoutNotchProvider.java"
            line="117"/>
    </issue>

    <issue
        id="DefaultLocale"
        message="Implicitly using the default locale is a common source of bugs: Use `String.format(Locale, ...)` instead">
        <location
            file="src/com/android/tools/idea/uibuilder/handlers/constraint/draw/ConstraintLayoutNotchProvider.java"
            line="118"/>
    </issue>

    <issue
        id="DefaultLocale"
        message="Implicitly using the default locale is a common source of bugs: Use `String.format(Locale, ...)` instead">
        <location
            file="src/com/android/tools/idea/uibuilder/handlers/constraint/draw/ConstraintLayoutNotchProvider.java"
            line="139"/>
    </issue>

    <issue
        id="DefaultLocale"
        message="Implicitly using the default locale is a common source of bugs: Use `String.format(Locale, ...)` instead">
        <location
            file="src/com/android/tools/idea/uibuilder/handlers/constraint/draw/ConstraintLayoutNotchProvider.java"
            line="146"/>
    </issue>

    <issue
        id="DefaultLocale"
        message="Implicitly using the default locale is a common source of bugs: Use `String.format(Locale, ...)` instead">
        <location
            file="src/com/android/tools/idea/uibuilder/handlers/constraint/targets/ConstraintResizeTarget.java"
            line="64"/>
    </issue>

    <issue
        id="DefaultLocale"
        message="Implicitly using the default locale is a common source of bugs: Use `String.format(Locale, ...)` instead">
        <location
            file="src/com/android/tools/idea/uibuilder/handlers/constraint/targets/ConstraintResizeTarget.java"
            line="72"/>
    </issue>

    <issue
        id="DefaultLocale"
        message="Implicitly using the default locale is a common source of bugs: Use `String.format(Locale, ...)` instead">
        <location
            file="src/com/android/tools/idea/uibuilder/handlers/constraint/targets/ConstraintResizeTarget.java"
            line="77"/>
    </issue>

    <issue
        id="DefaultLocale"
        message="Implicitly using the default locale is a common source of bugs: Use `String.format(Locale, ...)` instead">
        <location
            file="src/com/android/tools/idea/uibuilder/handlers/constraint/targets/ConstraintResizeTarget.java"
            line="82"/>
    </issue>

    <issue
        id="DefaultLocale"
        message="Implicitly using the default locale is a common source of bugs: Use `String.format(Locale, ...)` instead">
        <location
            file="src/com/android/tools/idea/uibuilder/scout/ConstraintSet.java"
            line="117"/>
    </issue>

    <issue
        id="DefaultLocale"
        message="Implicitly using the default locale is a common source of bugs: Use `String.format(Locale, ...)` instead">
        <location
            file="src/com/android/tools/idea/uibuilder/scout/ConstraintSet.java"
            line="124"/>
    </issue>

    <issue
        id="DefaultLocale"
        message="Implicitly using the default locale is a common source of bugs: Use `String.format(Locale, ...)` instead">
        <location
            file="src/com/android/tools/idea/uibuilder/scout/ConstraintSet.java"
            line="129"/>
    </issue>

    <issue
        id="DefaultLocale"
        message="Implicitly using the default locale is a common source of bugs: Use `String.format(Locale, ...)` instead">
        <location
            file="src/com/android/tools/idea/uibuilder/scout/ConstraintSet.java"
            line="134"/>
    </issue>

    <issue
        id="DefaultLocale"
        message="Implicitly using the default locale is a common source of bugs: Use `String.format(Locale, ...)` instead">
        <location
            file="src/com/android/tools/idea/uibuilder/scout/ConstraintSet.java"
            line="139"/>
    </issue>

    <issue
        id="DefaultLocale"
        message="Implicitly using the default locale is a common source of bugs: Use `toLowerCase(Locale)` instead. For strings meant to be internal use `Locale.ROOT`, otherwise `Locale.getDefault()`.">
        <location
            file="src/com/android/tools/idea/sampledata/CsvEditorProvider.kt"
            line="38"/>
    </issue>

    <issue
        id="DefaultLocale"
        message="Implicitly using the default locale is a common source of bugs: Use `String.format(Locale, ...)` instead">
        <location
            file="src/com/android/tools/idea/uibuilder/actions/GenerateLayoutTestSkeletonAction.java"
            line="276"/>
    </issue>

    <issue
        id="DefaultLocale"
        message="Implicitly using the default locale is a common source of bugs: Use `String.format(Locale, ...)` instead">
        <location
            file="src/com/android/tools/idea/uibuilder/handlers/constraint/targets/GuidelineCycleTarget.java"
            line="143"/>
    </issue>

    <issue
        id="DefaultLocale"
        message="Implicitly using the default locale is a common source of bugs: Use `String.format(Locale, ...)` instead">
        <location
            file="src/com/android/tools/idea/uibuilder/handlers/constraint/targets/GuidelineCycleTarget.java"
            line="147"/>
    </issue>

    <issue
        id="DefaultLocale"
        message="Implicitly using the default locale is a common source of bugs: Use `String.format(Locale, ...)` instead">
        <location
            file="src/com/android/tools/idea/uibuilder/handlers/constraint/targets/GuidelineCycleTarget.java"
            line="170"/>
    </issue>

    <issue
        id="DefaultLocale"
        message="Implicitly using the default locale is a common source of bugs: Use `String.format(Locale, ...)` instead">
        <location
            file="src/com/android/tools/idea/uibuilder/handlers/constraint/targets/GuidelineCycleTarget.java"
            line="177"/>
    </issue>

    <issue
        id="DefaultLocale"
        message="Implicitly using the default locale is a common source of bugs: Use `String.format(Locale, ...)` instead">
        <location
            file="src/com/android/tools/idea/uibuilder/handlers/constraint/targets/GuidelineTarget.java"
            line="309"/>
    </issue>

    <issue
        id="DefaultLocale"
        message="Implicitly using the default locale is a common source of bugs: Use `String.format(Locale, ...)` instead">
        <location
            file="src/com/android/tools/idea/uibuilder/handlers/constraint/targets/GuidelineTarget.java"
            line="313"/>
    </issue>

    <issue
        id="DefaultLocale"
        message="Implicitly using the default locale is a common source of bugs: Use `String.format(Locale, ...)` instead">
        <location
            file="src/com/android/tools/idea/uibuilder/layout3d/LayerDisplay.java"
            line="312"/>
    </issue>

    <issue
        id="DefaultLocale"
        message="Implicitly using the default locale is a common source of bugs: Use `String.format(Locale, ...)` instead">
        <location
            file="src/com/android/tools/idea/uibuilder/layout3d/LayerDisplay.java"
            line="317"/>
    </issue>

    <issue
        id="DefaultLocale"
        message="Implicitly using the default locale is a common source of bugs: Use `String.format(Locale, ...)` instead">
        <location
            file="src/com/android/tools/idea/uibuilder/layout3d/LayerDisplay.java"
            line="321"/>
    </issue>

    <issue
        id="DefaultLocale"
        message="Implicitly using the default locale is a common source of bugs: Use `String.format(Locale, ...)` instead">
        <location
            file="src/com/android/tools/idea/uibuilder/scout/RectangleGenerator.java"
            line="131"/>
    </issue>

    <issue
        id="DefaultLocale"
        message="Implicitly using the default locale is a common source of bugs: Use `String.format(Locale, ...)` instead">
        <location
            file="src/com/android/tools/idea/uibuilder/scout/RectangleGenerator.java"
            line="136"/>
    </issue>

    <issue
        id="DefaultLocale"
        message="Implicitly using the default locale is a common source of bugs: Use `String.format(Locale, ...)` instead">
        <location
            file="src/com/android/tools/idea/uibuilder/scout/RectangleGenerator.java"
            line="142"/>
    </issue>

    <issue
        id="DefaultLocale"
        message="Implicitly using the default locale is a common source of bugs: Use `String.format(Locale, ...)` instead">
        <location
            file="src/com/android/tools/idea/uibuilder/scout/RectangleGenerator.java"
            line="148"/>
    </issue>

    <issue
        id="DefaultLocale"
        message="Implicitly using the default locale is a common source of bugs: Use `String.format(Locale, ...)` instead">
        <location
            file="src/com/android/tools/idea/uibuilder/scene/target/ResizeWithSnapBaseTarget.java"
            line="175"/>
    </issue>

    <issue
        id="DefaultLocale"
        message="Implicitly using the default locale is a common source of bugs: Use `String.format(Locale, ...)` instead">
        <location
            file="src/com/android/tools/idea/uibuilder/scene/target/ResizeWithSnapBaseTarget.java"
            line="188"/>
    </issue>

    <issue
        id="DefaultLocale"
        message="Implicitly using the default locale is a common source of bugs: Use `toLowerCase(Locale)` instead. For strings meant to be internal use `Locale.ROOT`, otherwise `Locale.getDefault()`.">
        <location
            file="src/com/android/tools/idea/common/scene/Scene.java"
            line="655"/>
    </issue>

    <issue
        id="DefaultLocale"
        message="Implicitly using the default locale is a common source of bugs: Use `String.format(Locale, ...)` instead">
        <location
            file="src/com/android/tools/idea/uibuilder/scout/ScoutDirectConvert.java"
            line="252"/>
    </issue>

    <issue
        id="DefaultLocale"
        message="Implicitly using the default locale is a common source of bugs: Use `String.format(Locale, ...)` instead">
        <location
            file="src/com/android/tools/idea/uibuilder/surface/ScreenViewLayer.java"
            line="282"/>
    </issue>

    <issue
        id="DefaultLocale"
        message="Implicitly using the default locale is a common source of bugs: Use `String.format(Locale, ...)` instead">
        <location
            file="src/com/android/tools/idea/uibuilder/handlers/constraint/WidgetConstraintModel.java"
            line="630"/>
    </issue>

    <issue
        id="DefaultLocale"
        message="Implicitly using the default locale is a common source of bugs: Use `String.format(Locale, ...)` instead">
        <location
            file="src/com/android/tools/idea/uibuilder/mockup/editor/creators/WidgetCreator.java"
            line="234"/>
    </issue>

    <issue
        id="DefaultLocale"
        message="Implicitly using the default locale is a common source of bugs: Use `String.format(Locale, ...)` instead">
        <location
            file="src/com/android/tools/idea/uibuilder/mockup/editor/creators/WidgetCreator.java"
            line="236"/>
    </issue>

    <issue
        id="DefaultLocale"
        message="Implicitly using the default locale is a common source of bugs: Use `String.format(Locale, ...)` instead">
        <location
            file="src/com/android/tools/idea/uibuilder/mockup/editor/creators/WidgetCreator.java"
            line="248"/>
    </issue>

    <issue
        id="DefaultLocale"
        message="Implicitly using the default locale is a common source of bugs: Use `String.format(Locale, ...)` instead">
        <location
            file="src/com/android/tools/idea/uibuilder/mockup/editor/creators/WidgetCreator.java"
            line="250"/>
    </issue>

    <issue
        id="VisibleForTests"
        message="This method should only be accessed from tests or within private scope">
        <location
            file="src/com/android/tools/idea/uibuilder/property/editors/AddPropertyEditor.java"
            line="84"/>
    </issue>

    <issue
        id="VisibleForTests"
        message="This method should only be accessed from tests or within private scope">
        <location
            file="src/com/android/tools/idea/uibuilder/mockup/colorextractor/DoublesColorExtractor.java"
            line="145"/>
    </issue>

    <issue
        id="VisibleForTests"
        message="This method should only be accessed from tests or within private scope">
        <location
            file="src/com/android/tools/idea/common/error/IssuePanel.java"
            line="481"/>
    </issue>

    <issue
        id="VisibleForTests"
        message="This method should only be accessed from tests or within private scope">
        <location
            file="src/com/android/tools/idea/common/error/IssuePanel.java"
            line="481"/>
    </issue>

    <issue
        id="VisibleForTests"
        message="This method should only be accessed from tests or within private scope">
        <location
            file="src/com/android/tools/idea/common/error/IssuePanel.java"
            line="488"/>
    </issue>

    <issue
        id="VisibleForTests"
        message="This method should only be accessed from tests or within private scope">
        <location
            file="src/com/android/tools/idea/common/error/IssuePanel.java"
            line="488"/>
    </issue>

    <issue
        id="VisibleForTests"
        message="This method should only be accessed from tests or within private scope">
        <location
            file="src/com/android/tools/idea/common/model/NlComponent.java"
            line="101"/>
    </issue>

    <issue
        id="VisibleForTests"
        message="This method should only be accessed from tests or within private scope">
        <location
            file="src/com/android/tools/idea/common/model/NlComponent.java"
            line="101"/>
    </issue>

    <issue
        id="VisibleForTests"
        message="This method should only be accessed from tests or within private scope">
        <location
            file="src/com/android/tools/idea/uibuilder/property/editors/NlSlicePropertyEditor.java"
            line="72"/>
    </issue>

    <issue
        id="SwingWorker"
        message="Do not use `javax.swing.SwingWorker`, use `com.intellij.util.concurrency.SwingWorker` instead. See `go/do-not-freeze`.">
        <location
            file="src/com/android/tools/idea/uibuilder/mockup/colorextractor/DoublesColorExtractor.java"
            line="132"/>
    </issue>

    <issue
        id="WrongInvokeLater"
        message="Do not use `SwingUtilities.invokeLater`; use `Application.invokeLater` instead. See `go/do-not-freeze`.">
        <location
            file="src/com/android/tools/idea/uibuilder/property/editors/NlTableCellEditor.java"
            line="208"/>
    </issue>

    <issue
        id="WrongInvokeLater"
        message="Do not use `SwingUtilities.invokeLater`; use `Application.invokeLater` instead. See `go/do-not-freeze`.">
        <location
            file="src/com/android/tools/idea/uibuilder/property/editors/NlTableCellEditor.java"
            line="221"/>
    </issue>

    <issue
        id="WrongThread"
        message="Method getPalette is slow and thus should run on a worker thread, yet the currently inferred thread is the UI thread">
        <location
            file="src/com/android/tools/idea/uibuilder/palette/DataModel.java"
            line="230"/>
    </issue>

</issues>
